flexit_bacnet/__init__.py
flexit_bacnet/bacnet.py
flexit_bacnet/device.py
flexit_bacnet/nordic.py
flexit_bacnet/py.typed
flexit_bacnet-2.2.2.dist-info/LICENSE
flexit_bacnet-2.2.2.dist-info/METADATA
flexit_bacnet-2.2.2.dist-info/WHEEL
flexit_bacnet-2.2.2.dist-info/top_level.txt
flexit_bacnet-2.2.2.dist-info/RECORD
