Metadata-Version: 2.2
Name: flexit_bacnet
Version: 2.2.2
Summary: Client BACnet library for Flexit Nordic series of air handling units.
Author: Piotr Buliński
Project-URL: Homepage, https://github.com/piotrbulinski/flexit_bacnet
Project-URL: Bug Tracker, https://github.com/piotrbulinski/flexit_bacnet/issues
Classifier: Programming Language :: Python :: 3
Classifier: License :: OSI Approved :: MIT License
Classifier: Operating System :: OS Independent
Requires-Python: >=3.7
License-File: LICENSE
